{
    "hello.kpg": {
        "changeState": "",
        "name": "hello.kpg",
        "files": {
            "index.html": {
                "content": "<!DOCTYPE html>\n<html>\n<head>\n    <meta http-equiv=\"content-type\" content=\"text/html; charset=utf-8\" />\n    <title>Nasrin HTML Course</title>\n    <link href=\"style.css\" rel=\"stylesheet\" type=\"text/css\">\n    \n</head>\n<body>\n    <h1>Hello friends</h1>\n    <p>\n        look at this cute puppyss\n    </p>\n    <img src=\"puppy.jpg\">\n    <img src=\"dog.jpg\">\n    \n</body>\n</html>",
                "changeState": "",
                "editor": true,
                "fileName": "index.html",
                "fileType": "code",
                "path": "index.html",
                "src": "git",
                "url": "",
                "sha": "f3bf2fe747b5bceff2b880fe19e949dc27ce2e96",
                "changeStatus": ""
            },
            "puppy.jpg": {
                "type": "added",
                "fileName": "puppy.jpg",
                "locator": true,
                "editor": true,
                "src": "git",
                "fileType": "image",
                "path": "puppy.jpg",
                "fileObject": {},
                "content": "puppy.jpg",
                "url": "https://raw.githubusercontent.com/ntohidi/testKstudio/master/hello.kpg/puppy.jpg",
                "sha": "47b9e6f1df309dfa5e60f11d1b6daa22d813fa6e",
                "changeState": "added"
            },
            "readme.md": {
                "type": "added",
                "fileName": "readme.md",
                "locator": false,
                "editor": true,
                "src": "git",
                "fileType": "code",
                "path": "readme.md",
                "uploaded": false,
                "content": "# This is my very own course",
                "url": "",
                "changeState": "",
                "sha": "74f118455e3cb0b5a65e7d98bbeecfb52b67f90d",
                "changeStatus": ""
            },
            "dog.jpg": {
                "type": "added",
                "fileName": "dog.jpg",
                "locator": true,
                "editor": false,
                "src": "",
                "fileType": "image",
                "path": "dog.jpg",
                "uploaded": false,
                "content": "<!DOCTYPE html>\n<html>\n<head>\n    <meta http-equiv=\"content-type\" content=\"text/html; charset=utf-8\" />\n    <title>Nasrin HTML Course</title>\n    \n    <!--<style>-->\n    <!--    h1 {-->\n    <!--        color: green;-->\n    <!--    }-->\n    <!--    img {-->\n    <!--        width: 200px;-->\n    <!--    }-->\n    <!--</style>-->\n</head>\n<body>\n    <h1>Hello friends</h1>\n    <p>\n        look at this cute puppyss\n    </p>\n    <img src=\"puppy.jpg\">\n    <img src=\"dog.jpg\">\n    \n</body>\n</html>",
                "url": "https://www.petmd.com/sites/default/files/breedopedia/dalmatian.jpg",
                "changeState": "modified"
            },
            "style.css": {
                "type": "added",
                "fileName": "style.css",
                "locator": false,
                "editor": true,
                "src": "git",
                "fileType": "code",
                "path": "style.css",
                "uploaded": false,
                "content": "/* style.css Ì†ºÌæ®Ì†ΩÌ±ç */\n h1 {\n    color: green;\n}\nimg {\n    width: 200px;\n    height: 200px;\n    border: 2px solid green;\n}",
                "url": "",
                "changeState": "",
                "sha": "1e9b35319889f98366fcf0343f5465a49939d1d0",
                "changeStatus": ""
            },
            "app.js": {
                "type": "added",
                "fileName": "app.js",
                "locator": false,
                "editor": true,
                "src": "git",
                "fileType": "code",
                "path": "app.js",
                "uploaded": false,
                "content": "/* app.js Ì†æÌ¥ìÌ†ΩÌ±ç */\nconsole.log('hello')",
                "url": "",
                "changeState": "",
                "sha": "5feab0390112238cd4c99af762122d7092f50c2c",
                "changeStatus": ""
            },
            "main.js": {
                "type": "added",
                "fileName": "main.js",
                "locator": false,
                "editor": true,
                "src": "git",
                "fileType": "code",
                "path": "main.js",
                "uploaded": false,
                "content": "/* app.js Ì†æÌ¥ìÌ†ΩÌ±ç */\nconsole.log('hello from main')",
                "url": "",
                "changeState": "",
                "changeStatus": "",
                "sha": "33d45ef3e248bfca40faa0b387ef4e037c8f3b31"
            },
            "test.js": {
                "type": "added",
                "fileName": "test.js",
                "locator": false,
                "editor": true,
                "src": "git",
                "fileType": "code",
                "path": "test.js",
                "uploaded": false,
                "content": "/* app.js Ì†æÌ¥ìÌ†ΩÌ±ç */\nvar a = 3;\nconsole.log( a + 3);",
                "url": "",
                "changeState": "",
                "changeStatus": "",
                "oldPath": "main2.js",
                "sha": "ca3a2f3f1349270d01a764796e132b54cd839f2a"
            }
        },
        "changesLog": {},
        "pushed": true
    },
    "mypg.kpg": {
        "files": {
            "index.html": {
                "content": "<p>Hello Worldz</p>\n<img src=\"kidocode.jpg\">\n<video width=\"320\" height=\"240\" controls>\n  <source src=\"sample.mp4\" type=\"video/mp4\">\n</video>",
                "changeState": "",
                "editor": true,
                "fileType": "code",
                "fileName": "index.html",
                "path": "index.html",
                "url": "",
                "src": "git",
                "sha": "dd4aa079c9a6aaac8d7e1b56be919f92012d89d4",
                "changeStatus": ""
            },
            "app.css": {
                "content": "body {}",
                "changeState": "",
                "editor": true,
                "fileType": "code",
                "fileName": "app.css",
                "path": "app.css",
                "url": "",
                "src": "git",
                "sha": "2d91681f81650e8547ad94d5d21626e21474aae0",
                "changeStatus": ""
            },
            "app.js": {
                "content": "//console.log('hello world')",
                "changeState": "",
                "editor": true,
                "fileType": "code",
                "fileName": "app.js",
                "path": "app.js",
                "url": "",
                "src": "git",
                "sha": "9dc752d7e03930467d4ea4aa2feb2218b72bf05a",
                "changeStatus": ""
            },
            "readme.md": {
                "content": "This is a new playground, and make your best play here Ì†ΩÌ∏ç",
                "changeState": "",
                "editor": true,
                "fileType": "code",
                "fileName": "readme.md",
                "path": "readme.md",
                "url": "",
                "src": "git",
                "sha": "f1e3386355c457240d7775119ba3c2a1719c3d59",
                "changeStatus": ""
            },
            "kidocode.jpg": {
                "type": "added",
                "fileName": "kidocode.jpg",
                "locator": true,
                "editor": true,
                "src": "git",
                "fileType": "image",
                "path": "kidocode.jpg",
                "fileObject": {},
                "content": "kidocode.jpg",
                "url": "https://raw.githubusercontent.com/ntohidi/testKstudio/master/mypg.kpg/kidocode.jpg?token=AECYTANZLUAGUTKNJHJA5LS5JFJY6",
                "sha": "535d23086237c6d6a7352b1acb09e4ab70dd0dd2",
                "changeState": "added"
            },
            "sample.mp4": {
                "type": "added",
                "fileName": "sample.mp4",
                "locator": true,
                "editor": false,
                "src": "",
                "fileType": "video",
                "path": "sample.mp4",
                "uploaded": false,
                "content": "<p>Hello World</p>\n<img src=\"kidocode.jpg\">ss",
                "url": "https://sample-videos.com/video123/mp4/480/big_buck_bunny_480p_1mb.mp4",
                "changeState": "modified"
            }
        },
        "hash": "",
        "lins": {
            "scripts": [],
            "css": []
        },
        "name": "mypg.kpg",
        "caption": "newone.kpg",
        "changesLog": {},
        "changeState": "",
        "pushed": true,
        "oldName": "newone.kpg"
    },
    "testxx.kpg": {
        "files": {
            "index.html": {
                "content": "<p>Hello Worldzzzzz</p>\n<img src=\"kidocode.jpg\">\n<video width=\"320\" height=\"240\" controls>\n  <source src=\"sample.mp4\" type=\"video/mp4\">\n</video>\n",
                "changeState": "",
                "editor": true,
                "fileType": "code",
                "fileName": "index.html",
                "path": "index.html",
                "url": "",
                "src": "git",
                "sha": "dcb81669896889f399fe176a262bea66a9660c79",
                "changeStatus": ""
            },
            "app.css": {
                "content": "body {\n    background-image: url('bg.jpg');\n}\nvideo{\n    margin-top: 2rem;\n    display: block;\n    border: 5px solid #e6beaf;\n    border-radius: 10px;\n}\np{\n    color:green;\n    font-weight: 500;\n    \n}",
                "changeState": "",
                "editor": true,
                "fileType": "code",
                "fileName": "app.css",
                "path": "app.css",
                "url": "",
                "src": "git",
                "sha": "95ddf856fd61a40123fb7b753fac99ec37f2d94f",
                "changeStatus": ""
            },
            "app.js": {
                "content": "//console.log('hello world')\nvar a = 2;\nfunction func(x){\n    var v = x *2;\n    return v\n}\n\nconsole.log('calling my function...')\nconsole.log(func(4))\nconsole.log('Done')",
                "changeState": "",
                "editor": true,
                "fileType": "code",
                "fileName": "app.js",
                "path": "app.js",
                "url": "",
                "src": "git",
                "sha": "59bf466b05cf1b18992267a234b003b3211c1878",
                "changeStatus": ""
            },
            "readme.md": {
                "content": "This is a new playground, and make your best play here Ì†ΩÌ∏ç\n# I want to teach you how to add background image to your page, so come with me in my jurney Ì†ΩÌ±©Ì†ºÌøª‚ÄçÌ†ºÌæ®\n\nTo add background image to body, we need to add new attributr inside body selector:\n```\n    background-image: url('http://wta.wpengine.netdna-cdn.com/wp-content/uploads/2013/07/Color_03.jpg');\n```\n\nThat's it!\n### Easy Peasy Ì†æÌ¥ûÌ†ºÌøºÌ†ΩÌ≤ÉÌ†ºÌøºÌ†æÌ¥™\n",
                "changeState": "",
                "editor": true,
                "fileType": "code",
                "fileName": "readme.md",
                "path": "readme.md",
                "url": "",
                "src": "git",
                "sha": "05f58b8048bae7df93adbaff212801436ee41928",
                "changeStatus": ""
            },
            "kidocode.jpg": {
                "type": "added",
                "fileName": "kidocode.jpg",
                "locator": true,
                "editor": true,
                "src": "git",
                "fileType": "image",
                "path": "kidocode.jpg",
                "fileObject": {},
                "content": "kidocode.jpg",
                "url": "https://raw.githubusercontent.com/ntohidi/testKstudio/master/mypg.kpg/kidocode.jpg?token=AECYTANZLUAGUTKNJHJA5LS5JFJY6",
                "sha": "535d23086237c6d6a7352b1acb09e4ab70dd0dd2",
                "changeState": "added"
            },
            "sample.mp4": {
                "type": "added",
                "fileName": "sample.mp4",
                "locator": true,
                "editor": false,
                "src": "",
                "fileType": "video",
                "path": "sample.mp4",
                "uploaded": false,
                "content": "<p>Hello World</p>\n<img src=\"kidocode.jpg\">ss",
                "url": "https://sample-videos.com/video123/mp4/480/big_buck_bunny_480p_1mb.mp4",
                "changeState": "added"
            },
            "bg.jpg": {
                "type": "added",
                "fileName": "bg.jpg",
                "locator": true,
                "editor": false,
                "src": "",
                "fileType": "image",
                "path": "bg.jpg",
                "uploaded": false,
                "content": "",
                "url": "http://wta.wpengine.netdna-cdn.com/wp-content/uploads/2013/07/Color_03.jpg",
                "changeState": "added"
            }
        },
        "hash": "",
        "lins": {
            "scripts": [],
            "css": []
        },
        "name": "testxx.kpg",
        "caption": "newone.kpg",
        "changesLog": {},
        "changeState": "",
        "pushed": true,
        "oldName": "mypg_0.kpg"
    },
    "boogh.kpg": {
        "files": {
            "index.html": {
                "content": "<p>Hello Worldzz111</p>\n",
                "changeState": "added",
                "editor": true,
                "fileType": "code",
                "fileName": "index.html",
                "path": "index.html",
                "url": "",
                "src": "git",
                "sha": "87c1f30a4d4b6f71a6caaa1210a33b4e7c85de92",
                "changeStatus": ""
            },
            "app.css": {
                "content": "body {}",
                "changeState": "added",
                "editor": true,
                "fileType": "code",
                "fileName": "app.css",
                "path": "app.css",
                "url": "",
                "src": "git",
                "sha": "2d91681f81650e8547ad94d5d21626e21474aae0",
                "changeStatus": ""
            },
            "app.js": {
                "content": "//console.log('hello world')\nvar a = 2;",
                "changeState": "added",
                "editor": true,
                "fileType": "code",
                "fileName": "app.js",
                "path": "app.js",
                "url": "",
                "src": "git",
                "sha": "67dd8131a0e9961d54c546ce7927b3710430529b",
                "changeStatus": ""
            },
            "readme.md": {
                "content": "This is a new playground, and make your best play here Ì†ΩÌ∏ç\n# yeayyyy\n## hoooo",
                "changeState": "added",
                "editor": true,
                "fileType": "code",
                "fileName": "readme.md",
                "path": "readme.md",
                "url": "",
                "src": "git",
                "sha": "86f833bf6adca5430cde4eea1eb46705f601b39a",
                "changeStatus": ""
            },
            "kidocode.jpg": {
                "type": "added",
                "fileName": "kidocode.jpg",
                "locator": true,
                "editor": true,
                "src": "git",
                "fileType": "image",
                "path": "kidocode.jpg",
                "fileObject": {},
                "content": "kidocode.jpg",
                "url": "https://raw.githubusercontent.com/ntohidi/testKstudio/master/mypg.kpg/kidocode.jpg?token=AECYTANZLUAGUTKNJHJA5LS5JFJY6",
                "sha": "535d23086237c6d6a7352b1acb09e4ab70dd0dd2",
                "changeState": "added"
            },
            "sample.mp4": {
                "type": "added",
                "fileName": "sample.mp4",
                "locator": true,
                "editor": false,
                "src": "",
                "fileType": "video",
                "path": "sample.mp4",
                "uploaded": false,
                "content": "<p>Hello World</p>\n<img src=\"kidocode.jpg\">ss",
                "url": "https://sample-videos.com/video123/mp4/480/big_buck_bunny_480p_1mb.mp4",
                "changeState": "added"
            }
        },
        "hash": "",
        "lins": {
            "scripts": [],
            "css": []
        },
        "name": "boogh.kpg",
        "caption": "newone.kpg",
        "changesLog": {},
        "changeState": "renamed",
        "pushed": true,
        "oldName": "testxx_0.kpg"
    },
    "kitkat.kpg": {
        "files": {
            "index.html": {
                "content": "<p>Hello World</p>",
                "changeState": "",
                "editor": true,
                "fileType": "code",
                "fileName": "index.html",
                "path": "index.html",
                "url": "",
                "src": "git",
                "sha": "92f9a3de160337a5b33a4a04b06fb339f56d45ae",
                "changeStatus": ""
            },
            "app.css": {
                "content": "body {}",
                "changeState": "",
                "editor": true,
                "fileType": "code",
                "fileName": "app.css",
                "path": "app.css",
                "url": "",
                "src": "git",
                "sha": "2d91681f81650e8547ad94d5d21626e21474aae0",
                "changeStatus": ""
            },
            "app.js": {
                "content": "//console.log('hello world')",
                "changeState": "",
                "editor": true,
                "fileType": "code",
                "fileName": "app.js",
                "path": "app.js",
                "url": "",
                "src": "git",
                "sha": "9dc752d7e03930467d4ea4aa2feb2218b72bf05a",
                "changeStatus": ""
            },
            "readme.md": {
                "content": "This is a new playground, and make your best play hesre Ì†ΩÌ∏ç",
                "changeState": "modified",
                "editor": true,
                "fileType": "code",
                "fileName": "readme.md",
                "path": "readme.md",
                "url": "",
                "src": "git"
            }
        },
        "hash": "",
        "lins": {
            "scripts": [],
            "css": []
        },
        "name": "kitkat.kpg",
        "caption": "kitkat.kpg",
        "changesLog": {},
        "changeState": "",
        "pushed": true
    },
    "test.kpg": {
        "files": {
            "index.html": {
                "content": "<p>Hello World</p>",
                "changeState": "",
                "editor": true,
                "fileType": "code",
                "fileName": "index.html",
                "path": "index.html",
                "url": "",
                "src": "git",
                "sha": "92f9a3de160337a5b33a4a04b06fb339f56d45ae",
                "changeStatus": ""
            },
            "app.css": {
                "content": "body {}",
                "changeState": "",
                "editor": true,
                "fileType": "code",
                "fileName": "app.css",
                "path": "app.css",
                "url": "",
                "src": "git",
                "sha": "2d91681f81650e8547ad94d5d21626e21474aae0",
                "changeStatus": ""
            },
            "app.js": {
                "content": "//console.log('hello world')",
                "changeState": "",
                "editor": true,
                "fileType": "code",
                "fileName": "app.js",
                "path": "app.js",
                "url": "",
                "src": "git",
                "sha": "9dc752d7e03930467d4ea4aa2feb2218b72bf05a",
                "changeStatus": ""
            },
            "readme.md": {
                "content": "This is a new playground, and make your best play here Ì†ΩÌ∏ç",
                "changeState": "added",
                "editor": true,
                "fileType": "code",
                "fileName": "readme.md",
                "path": "readme.md",
                "url": "",
                "src": "git"
            }
        },
        "hash": "",
        "lins": {
            "scripts": [],
            "css": []
        },
        "name": "test.kpg",
        "caption": "test.kpg",
        "changesLog": {},
        "changeState": "",
        "pushed": true
    }
}